turbine_models/__init__.py
turbine_models/make_turbine_data_summary.py
turbine_models/parser.py
turbine_models/turbine_spell_checker_tools.py
turbine_models/data/Distributed/2019COE_DW100_100kW_27.6.csv
turbine_models/data/Distributed/2019COE_DW20_20kW_12.4.csv
turbine_models/data/Distributed/BergeyExcel10_8.9kW_7.csv
turbine_models/data/Distributed/BergeyExcel15_15.6kW_9.6.csv
turbine_models/data/Distributed/Bestwind30_27.2kW_13.1.csv
turbine_models/data/Distributed/CF10A_10kW_11.15.csv
turbine_models/data/Distributed/CF11A_11kW_11.15.csv
turbine_models/data/Distributed/CF11_11kW_9.36.csv
turbine_models/data/Distributed/CF15_15kW_11.15.csv
turbine_models/data/Distributed/CF20_20kW_13.1.csv
turbine_models/data/Distributed/EWT_DW52_900kW_51.5.csv
turbine_models/data/Distributed/EWT_DW54X_1MW_54.1.csv
turbine_models/data/Distributed/EWT_DW54_900kW_54.csv
turbine_models/data/Distributed/EWT_DW58_1MW_58.csv
turbine_models/data/Distributed/EWT_DW61_1MW_60.9.csv
turbine_models/data/Distributed/EntegrityEW50_50kW_15.csv
turbine_models/data/Distributed/FortisMontana_3.31kW_5.04.csv
turbine_models/data/Distributed/GhrepowerFD21-50_61.2kW_21.5.csv
turbine_models/data/Distributed/Jacobs31-20_12kW_9.45.csv
turbine_models/data/Distributed/Kestrele400nb_2.5kW_4.csv
turbine_models/data/Distributed/NPS100B-21_100kW_20.7.csv
turbine_models/data/Distributed/NPS100B-24C_95kW_24.4.csv
turbine_models/data/Distributed/NPS100B-24_95kW_23.6.csv
turbine_models/data/Distributed/NPS100C-21_100kW_20.7.csv
turbine_models/data/Distributed/NPS100C-24_95kW_24.4.csv
turbine_models/data/Distributed/NPS100C-27_90kW_27.4.csv
turbine_models/data/Distributed/NPS100C-28_90kW_27.6.csv
turbine_models/data/Distributed/NPS100C-28_90kW_28.csv
turbine_models/data/Distributed/NPS60C-24_60kW_24.4.csv
turbine_models/data/Distributed/PikaT701_1.5kW_3.csv
turbine_models/data/Distributed/SD6_5.2kW_5.5.csv
turbine_models/data/Distributed/SWIFT_1kW_2.1.csv
turbine_models/data/Distributed/Skystream3.7_2.1kW_3.7.csv
turbine_models-0.1.1.dist-info/licenses/LICENSE.txt
turbine_models-0.1.1.dist-info/METADATA
turbine_models-0.1.1.dist-info/WHEEL
turbine_models-0.1.1.dist-info/top_level.txt
turbine_models-0.1.1.dist-info/RECORD
