Metadata-Version: 2.4
Name: turbine-models
Version: 0.1.1
Summary: Retrieves power curves and key data for commonly used turbine models in industry and R&D community.
Author: Travis Williams
Author-email: Patrick Duffy <patrick.duffy@nrel.gov>
Maintainer-email: Patrick Duffy <patrick.duffy@nrel.gov>, Elenya Grant <elenya.grant@nrel.gov>, Rob Hammond <rob.hammond@nrel.gov>
Project-URL: source, https://github.com/NREL/turbine-models
Project-URL: documentation, https://nrel.github.io/turbine-models/
Project-URL: issues, https://github.com/NREL/turbine-models/issues
Project-URL: changelog, https://github.com/NREL/turbine-models/blob/main/RELEASE.md
Keywords: python3,turbine-library,wind-turbines,power-curve,power-curves,data,wind-energy
Classifier: Development Status :: 4 - Beta
Classifier: License :: OSI Approved :: BSD License
Classifier: Natural Language :: English
Classifier: Operating System :: MacOS
Classifier: Operating System :: Microsoft :: Windows
Classifier: Operating System :: POSIX :: Linux
Classifier: Operating System :: Unix
Classifier: Programming Language :: Python
Classifier: Programming Language :: Python :: 3 :: Only
Classifier: Programming Language :: Python :: 3.10
Classifier: Programming Language :: Python :: 3.11
Classifier: Programming Language :: Python :: 3.12
Classifier: Programming Language :: Python :: 3.13
Classifier: Topic :: Scientific/Engineering
Classifier: Topic :: Software Development :: Libraries
Classifier: Topic :: Software Development :: Libraries :: Python Modules
Classifier: Topic :: Utilities
Requires-Python: <3.14,>=3.10
License-File: LICENSE.txt
Requires-Dist: numpy
Requires-Dist: pandas
Requires-Dist: matplotlib
Requires-Dist: pyyaml
Requires-Dist: pyyaml-include
Provides-Extra: develop
Requires-Dist: pytest; extra == "develop"
Requires-Dist: pytest-subtests; extra == "develop"
Requires-Dist: pytest-dependency; extra == "develop"
Requires-Dist: responses; extra == "develop"
Requires-Dist: jupyter-book; extra == "develop"
Requires-Dist: sphinxcontrib-napoleon; extra == "develop"
Dynamic: license-file
